easyprofile.py
easyprofile-0.1.5.dist-info/LICENSE.txt
easyprofile-0.1.5.dist-info/WHEEL
easyprofile-0.1.5.dist-info/METADATA
easyprofile-0.1.5.dist-info/RECORD
