Metadata-Version: 2.1
Name: easyprofile
Version: 0.1.5
Summary: Easy context-based profiling with logging support
Author-email: Nicolas Tessore <n.tessore@ucl.ac.uk>
Requires-Python: >=3.7
Classifier: License :: OSI Approved :: MIT License
Project-URL: Homepage, https://github.com/ntessore/easyprofile
Project-URL: Issues, https://github.com/ntessore/easyprofile/issues
